CHANGELOG.txt
LICENCE.txt
MANIFEST.in
README.md
setup.py
MLecon/__init__.py
MLecon.egg-info/PKG-INFO
MLecon.egg-info/SOURCES.txt
MLecon.egg-info/dependency_links.txt
MLecon.egg-info/requires.txt
MLecon.egg-info/top_level.txt
MLecon/Matching/Geokernel.py
MLecon/Matching/Matching_kernel.py
MLecon/Matching/Matching_nn.py
MLecon/Matching/__init__.py
MLecon/Regression/Regression_kernel.py
MLecon/Regression/Regression_sieves.py
MLecon/Regression/Residuals.py
MLecon/Regression/__init__.py