Metadata-Version: 2.1
Name: MLecon
Version: 0.0.3
Summary: Package with all the functions
Home-page: UNKNOWN
Author: Anzony Quispe
Author-email: anzony.quispe@gmail.com
License: MIT
Keywords: Machine Learning
Platform: UNKNOWN
Classifier: Development Status :: 5 - Production/Stable
Classifier: Intended Audience :: Education
Classifier: Operating System :: Microsoft :: Windows :: Windows 10
Classifier: License :: OSI Approved :: MIT License
Classifier: Programming Language :: Python :: 3
